{"users":[{"name":"Jordan","age":"35","username":"JordanOfTroy - UMM","email":"email@email.com","uuid":"4be69038-cd9a-4364-a11d-8ac3c3f3434e"},{"name":"Shelbie","age":"25","username":"Bert","email":"email@email.com","uuid":"95606fcb-b35b-46fd-8ca8-4aefa1fc01b5"},{"name":"Sokka","age":"25","username":"BoomerangGuy","email":"email@email.com","uuid":"76a24ffe-a78d-4dd9-a6a1-513b4018dd03"},{"name":"Mom","age":"35","username":"Boss Lady of AWESOMENESS","email":"fake@email.com","uuid":"c5f1725a-8083-4396-9f6d-0cfc88c1056d"}]}